{
    "20210330124711": {
        "live_id": "1022:2321324620428801868179", 
        "url": "https://weibo.com/l/wblive/p/show/1022:2321324620428801868179", 
        "url_mobile": "https://weibo.com/l/wblive/app/h5_compatible?live_id=1022:2321324620428801868179", 
        "live_stream_id": "4620429215403690", 
        "live_flv_url": "https://plwb00.live.weibo.com/alicdn/4620429215403690.flv", 
        "live_hls_url": "https://plwb00.live.weibo.com/alicdn/4620429215403690.m3u8", 
        "live_replay_url": "http://live.video.weibocdn.com/4620429215403690_index.m3u8"
    }
}